tycho/__init__.py
tycho/actions.py
tycho/api-schema.yaml
tycho/api.py
tycho/client.py
tycho/compute.py
tycho/config.py
tycho/context.py
tycho/core.py
tycho/dockerc.py
tycho/exceptions.py
tycho/factory.py
tycho/kube.py
tycho/model.py
tycho/tycho_utils.py
tycho/conf/app-defaults.yaml
tycho/conf/app-registry.yaml
tycho/conf/tycho.yaml
tycho/template/clusterrole.yaml
tycho/template/clusterrolebinding.yaml
tycho/template/mapping.yaml
tycho/template/patch.yaml
tycho/template/pod.yaml
tycho/template/pv.yaml
tycho/template/pvc.yaml
tycho/template/service.yaml
tycho_api-1.17.3.dist-info/LICENSE.txt
tycho_api-1.17.3.dist-info/METADATA
tycho_api-1.17.3.dist-info/WHEEL
tycho_api-1.17.3.dist-info/entry_points.txt
tycho_api-1.17.3.dist-info/top_level.txt
tycho_api-1.17.3.dist-info/RECORD
